{
    "nodes": [
        {
            "id": 0,
            "value": 1,
            "name": "Inhibition",
            "trigger": 1,
            "group": 0
        },
        {
            "id": 1,
            "value": 4,
            "name": "Dll4|Dll4|Dll4|Dll4",
            "trigger": 0,
            "group": 4
        },
        {
            "id": 2,
            "value": 1,
            "name": "mediated",
            "trigger": 1,
            "group": 12
        },
        {
            "id": 3,
            "value": 3,
            "name": "signaling|signaling|signaling",
            "trigger": 1,
            "group": 11
        },
        {
            "id": 4,
            "value": 1,
            "name": "induces",
            "trigger": 1,
            "group": 12
        },
        {
            "id": 5,
            "value": 1,
            "name": "proliferation",
            "trigger": 1,
            "group": 7
        },
        {
            "id": 6,
            "value": 1,
            "name": "vessels",
            "trigger": 0,
            "group": 1
        },
        {
            "id": 7,
            "value": 1,
            "name": "tissue",
            "trigger": 0,
            "group": 5
        },
        {
            "id": 8,
            "value": 1,
            "name": "Vascular",
            "trigger": 0,
            "group": 1
        },
        {
            "id": 9,
            "value": 1,
            "name": "development",
            "trigger": 1,
            "group": 9
        },
        {
            "id": 10,
            "value": 1,
            "name": "dependent",
            "trigger": 1,
            "group": 12
        },
        {
            "id": 11,
            "value": 1,
            "name": "interaction",
            "trigger": 1,
            "group": 10
        },
        {
            "id": 12,
            "value": 1,
            "name": "stroma",
            "trigger": 0,
            "group": 5
        },
        {
            "id": 13,
            "value": 1,
            "name": "tissues",
            "trigger": 0,
            "group": 5
        },
        {
            "id": 14,
            "value": 1,
            "name": "hierarchic network",
            "trigger": 0,
            "group": 5
        },
        {
            "id": 15,
            "value": 1,
            "name": "formation",
            "trigger": 1,
            "group": 9
        },
        {
            "id": 16,
            "value": 1,
            "name": "recruitment",
            "trigger": 1,
            "group": 6
        },
        {
            "id": 17,
            "value": 1,
            "name": "pericytes",
            "trigger": 0,
            "group": 8
        },
        {
            "id": 18,
            "value": 5,
            "name": "Notch|Notch|Notch|Notch|Notch",
            "trigger": 0,
            "group": 4
        },
        {
            "id": 19,
            "value": 1,
            "name": "Jagged",
            "trigger": 0,
            "group": 4
        },
        {
            "id": 20,
            "value": 1,
            "name": "Delta",
            "trigger": 0,
            "group": 4
        },
        {
            "id": 21,
            "value": 1,
            "name": "play a critical role",
            "trigger": 1,
            "group": 13
        },
        {
            "id": 22,
            "value": 1,
            "name": "VEGF",
            "trigger": 0,
            "group": 4
        },
        {
            "id": 23,
            "value": 1,
            "name": "regulates",
            "trigger": 1,
            "group": 13
        },
        {
            "id": 24,
            "value": 1,
            "name": "arterial",
            "trigger": 0,
            "group": 1
        },
        {
            "id": 25,
            "value": 1,
            "name": "specification",
            "trigger": 1,
            "group": 9
        },
        {
            "id": 26,
            "value": 1,
            "name": "maturation",
            "trigger": 1,
            "group": 9
        },
        {
            "id": 27,
            "value": 1,
            "name": "Dll4 extracellular domain",
            "trigger": 0,
            "group": 4
        },
        {
            "id": 28,
            "value": 1,
            "name": "leads",
            "trigger": 1,
            "group": 12
        },
        {
            "id": 29,
            "value": 1,
            "name": "inhibition",
            "trigger": 1,
            "group": 0
        },
        {
            "id": 30,
            "value": 1,
            "name": "increased",
            "trigger": 1,
            "group": 12
        },
        {
            "id": 31,
            "value": 1,
            "name": "vascular",
            "trigger": 0,
            "group": 1
        },
        {
            "id": 32,
            "value": 1,
            "name": "proliferation",
            "trigger": 1,
            "group": 7
        },
        {
            "id": 33,
            "value": 1,
            "name": "defective",
            "trigger": 1,
            "group": 0
        },
        {
            "id": 34,
            "value": 1,
            "name": "maturation",
            "trigger": 1,
            "group": 9
        },
        {
            "id": 35,
            "value": 1,
            "name": "forming",
            "trigger": 1,
            "group": 9
        },
        {
            "id": 36,
            "value": 1,
            "name": "vessels",
            "trigger": 0,
            "group": 1
        },
        {
            "id": 37,
            "value": 2,
            "name": "reduced|reduced",
            "trigger": 1,
            "group": 0
        },
        {
            "id": 38,
            "value": 1,
            "name": "vessel lumen",
            "trigger": 0,
            "group": 2
        },
        {
            "id": 39,
            "value": 1,
            "name": "pericyte",
            "trigger": 0,
            "group": 8
        },
        {
            "id": 40,
            "value": 1,
            "name": "recruitment",
            "trigger": 1,
            "group": 6
        },
        {
            "id": 41,
            "value": 1,
            "name": "vascular",
            "trigger": 0,
            "group": 1
        },
        {
            "id": 42,
            "value": 1,
            "name": "sDll4",
            "trigger": 0,
            "group": 4
        },
        {
            "id": 43,
            "value": 1,
            "name": "induced",
            "trigger": 1,
            "group": 12
        },
        {
            "id": 44,
            "value": 1,
            "name": "defective",
            "trigger": 1,
            "group": 0
        },
        {
            "id": 45,
            "value": 1,
            "name": "vascular",
            "trigger": 0,
            "group": 1
        },
        {
            "id": 46,
            "value": 1,
            "name": "response",
            "trigger": 1,
            "group": 9
        },
        {
            "id": 47,
            "value": 1,
            "name": "tumor",
            "trigger": 0,
            "group": 3
        },
        {
            "id": 48,
            "value": 1,
            "name": "leading",
            "trigger": 1,
            "group": 12
        },
        {
            "id": 49,
            "value": 1,
            "name": "reduced",
            "trigger": 1,
            "group": 0
        },
        {
            "id": 50,
            "value": 1,
            "name": "tumor",
            "trigger": 0,
            "group": 3
        },
        {
            "id": 51,
            "value": 1,
            "name": "growth",
            "trigger": 1,
            "group": 7
        },
        {
            "id": 52,
            "value": 1,
            "name": "tumors",
            "trigger": 0,
            "group": 3
        },
        {
            "id": 53,
            "value": 1,
            "name": "induced",
            "trigger": 1,
            "group": 12
        },
        {
            "id": 54,
            "value": 1,
            "name": "pathway",
            "trigger": 1,
            "group": 11
        }
    ],
    "links": [
        {
            "source": 0,
            "target": 3,
            "value": 2
        },
        {
            "source": 5,
            "target": 6,
            "value": 2
        },
        {
            "source": 9,
            "target": 8,
            "value": 2
        },
        {
            "source": 16,
            "target": 17,
            "value": 2
        },
        {
            "source": 28,
            "target": 29,
            "value": 2
        },
        {
            "source": 28,
            "target": 27,
            "value": 2
        },
        {
            "source": 29,
            "target": 3,
            "value": 2
        },
        {
            "source": 30,
            "target": 32,
            "value": 2
        },
        {
            "source": 33,
            "target": 34,
            "value": 2
        },
        {
            "source": 40,
            "target": 39,
            "value": 2
        },
        {
            "source": 44,
            "target": 46,
            "value": 2
        },
        {
            "source": 51,
            "target": 50,
            "value": 2
        },
        {
            "source": 4,
            "target": 5,
            "value": 2
        },
        {
            "source": 4,
            "target": 0,
            "value": 2
        },
        {
            "source": 10,
            "target": 9,
            "value": 2
        },
        {
            "source": 11,
            "target": 12,
            "value": 2
        },
        {
            "source": 11,
            "target": 13,
            "value": 2
        },
        {
            "source": 23,
            "target": 1,
            "value": 2
        },
        {
            "source": 23,
            "target": 26,
            "value": 2
        },
        {
            "source": 32,
            "target": 31,
            "value": 2
        },
        {
            "source": 34,
            "target": 31,
            "value": 2
        },
        {
            "source": 35,
            "target": 36,
            "value": 2
        },
        {
            "source": 37,
            "target": 38,
            "value": 2
        },
        {
            "source": 37,
            "target": 40,
            "value": 2
        },
        {
            "source": 43,
            "target": 44,
            "value": 2
        },
        {
            "source": 43,
            "target": 42,
            "value": 2
        },
        {
            "source": 49,
            "target": 51,
            "value": 2
        },
        {
            "source": 48,
            "target": 51,
            "value": 2
        },
        {
            "source": 48,
            "target": 44,
            "value": 2
        },
        {
            "source": 53,
            "target": 54,
            "value": 2
        },
        {
            "source": 26,
            "target": 24,
            "value": 2
        },
        {
            "source": 25,
            "target": 24,
            "value": 2
        },
        {
            "source": 23,
            "target": 1,
            "value": 2
        },
        {
            "source": 23,
            "target": 25,
            "value": 2
        },
        {
            "source": 3,
            "target": 18,
            "value": 2
        },
        {
            "source": 3,
            "target": 1,
            "value": 2
        },
        {
            "source": 3,
            "target": 18,
            "value": 2
        },
        {
            "source": 54,
            "target": 1,
            "value": 2
        },
        {
            "source": 54,
            "target": 18,
            "value": 2
        },
        {
            "source": 2,
            "target": 1,
            "value": 2
        },
        {
            "source": 2,
            "target": 3,
            "value": 2
        },
        {
            "source": 15,
            "target": 14,
            "value": 2
        },
        {
            "source": 21,
            "target": 9,
            "value": 2
        },
        {
            "source": 21,
            "target": 19,
            "value": 2
        },
        {
            "source": 21,
            "target": 9,
            "value": 2
        },
        {
            "source": 21,
            "target": 20,
            "value": 2
        },
        {
            "source": 46,
            "target": 45,
            "value": 2
        }
    ]
}