{
    "name": "ROOT",
    "children": [
        {
            "name": "C0",
            "children": [
                {
                    "name": "human",
                    "value": 23
                },
                {
                    "name": "human",
                    "value": 23
                }
            ]
        },
        {
            "name": "C1",
            "children": [
                {
                    "name": "prothrombin kringle-2",
                    "value": 16
                },
                {
                    "name": "prothrombin kringle-2",
                    "value": 16
                }
            ]
        },
        {
            "name": "C2",
            "children": [
                {
                    "name": "B16F10 melanoma",
                    "value": 18
                },
                {
                    "name": "B16F10 melanoma cells",
                    "value": 17
                },
                {
                    "name": "B16F10 melanoma",
                    "value": 18
                },
                {
                    "name": "B16F10 melanoma",
                    "value": 18
                }
            ]
        },
        {
            "name": "C3",
            "children": [
                {
                    "name": "metastasis",
                    "value": 23
                },
                {
                    "name": "metastasis",
                    "value": 23
                }
            ]
        },
        {
            "name": "C4",
            "children": [
                {
                    "name": "inhibition",
                    "value": 23
                },
                {
                    "name": "inhibition",
                    "value": 23
                }
            ]
        },
        {
            "name": "C5",
            "children": [
                {
                    "name": "neovascularization",
                    "value": 20
                },
                {
                    "name": "neovascularization",
                    "value": 21
                }
            ]
        },
        {
            "name": "C6",
            "children": [
                {
                    "name": "reduction",
                    "value": 23
                },
                {
                    "name": "reduction",
                    "value": 23
                }
            ]
        },
        {
            "name": "C7",
            "children": [
                {
                    "name": "matrix metalloproteinase",
                    "value": 21
                },
                {
                    "name": "matrix metalloproteinase",
                    "value": 21
                }
            ]
        },
        {
            "name": "C8",
            "children": [
                {
                    "name": "expression",
                    "value": 24
                },
                {
                    "name": "expression",
                    "value": 24
                }
            ]
        },
        {
            "name": "C9",
            "children": [
                {
                    "name": "tumor",
                    "value": 23
                },
                {
                    "name": "tumor",
                    "value": 23
                }
            ]
        },
        {
            "name": "C10",
            "children": [
                {
                    "name": "rk-2",
                    "value": 20
                },
                {
                    "name": "rk-2",
                    "value": 19
                },
                {
                    "name": "rk-2",
                    "value": 20
                },
                {
                    "name": "rk-2",
                    "value": 20
                },
                {
                    "name": "rk-2",
                    "value": 20
                }
            ]
        },
        {
            "name": "C11",
            "children": [
                {
                    "name": "mouse",
                    "value": 23
                },
                {
                    "name": "mouse",
                    "value": 23
                },
                {
                    "name": "mouse",
                    "value": 23
                }
            ]
        },
        {
            "name": "C12",
            "children": [
                {
                    "name": "reduced",
                    "value": 22
                },
                {
                    "name": "diminished",
                    "value": 22
                }
            ]
        },
        {
            "name": "C13",
            "children": [
                {
                    "name": "lung",
                    "value": 23
                },
                {
                    "name": "lung",
                    "value": 23
                }
            ]
        }
    ]
}