{
    "nodes": [
        {
            "id": "T1000",
            "name": "men",
            "group": 1,
            "trigger": 0,
            "value": 23
        },
        {
            "id": "T1001",
            "name": "women",
            "group": 1,
            "trigger": 0,
            "value": 23
        },
        {
            "id": "T1",
            "name": "impaired",
            "group": 4,
            "trigger": 1,
            "value": 22
        },
        {
            "id": "T3",
            "name": "angiogenesis",
            "group": 0,
            "trigger": 1,
            "value": 22
        },
        {
            "id": "T1002",
            "name": "patients",
            "group": 1,
            "trigger": 0,
            "value": 22
        },
        {
            "id": "T7",
            "name": "revascularization",
            "group": 0,
            "trigger": 1,
            "value": 23
        },
        {
            "id": "T8",
            "name": "vein grafts",
            "group": 2,
            "trigger": 0,
            "value": 23
        },
        {
            "id": "T9",
            "name": "AAV serotypes",
            "group": 7,
            "trigger": 0,
            "value": 18
        },
        {
            "id": "T11",
            "name": "angiogenic",
            "group": 0,
            "trigger": 1,
            "value": 22
        },
        {
            "id": "T12",
            "name": "progenitor cells",
            "group": 6,
            "trigger": 0,
            "value": 23
        },
        {
            "id": "T2",
            "name": "obtain",
            "group": 3,
            "trigger": 1,
            "value": 22
        },
        {
            "id": "T14",
            "name": "blood vessels",
            "group": 2,
            "trigger": 0,
            "value": 22
        },
        {
            "id": "T15",
            "name": "ischemic tissue",
            "group": 5,
            "trigger": 0,
            "value": 22
        }
    ],
    "links": [
        {
            "source": "T1",
            "target": "T3",
            "value": 2
        },
        {
            "source": "T2",
            "target": "T14",
            "value": 2
        }
    ]
}