{
    "name": "ROOT",
    "children": [
        {
            "name": "C0",
            "children": [
                {
                    "name": "fibrinolytic",
                    "value": 23
                },
                {
                    "name": "fibrinolytic",
                    "value": 23
                },
                {
                    "name": "fibrinolytic",
                    "value": 23
                }
            ]
        },
        {
            "name": "C1",
            "children": [
                {
                    "name": "matrix metalloproteinase",
                    "value": 21
                },
                {
                    "name": "matrix metalloproteinase",
                    "value": 21
                }
            ]
        },
        {
            "name": "C2",
            "children": [
                {
                    "name": "systems",
                    "value": 23
                },
                {
                    "name": "systems",
                    "value": 23
                },
                {
                    "name": "systems",
                    "value": 22
                }
            ]
        },
        {
            "name": "C3",
            "children": [
                {
                    "name": "MMP",
                    "value": 23
                },
                {
                    "name": "MMP",
                    "value": 23
                }
            ]
        }
    ]
}