{
    "name": "ROOT",
    "children": [
        {
            "name": "C0",
            "children": [
                {
                    "name": "targeted",
                    "value": 23
                },
                {
                    "name": "targeted",
                    "value": 23
                }
            ]
        },
        {
            "name": "C1",
            "children": [
                {
                    "name": "cyclic RGD-modified heparin derivative",
                    "value": 16
                },
                {
                    "name": "cRGD-modified heparin derivative",
                    "value": 16
                },
                {
                    "name": "cRGD-modified heparin derivative",
                    "value": 17
                }
            ]
        },
        {
            "name": "C2",
            "children": [
                {
                    "name": "angiogenesis",
                    "value": 23
                },
                {
                    "name": "angiogenesis",
                    "value": 23
                }
            ]
        },
        {
            "name": "C3",
            "children": [
                {
                    "name": "tumor",
                    "value": 23
                },
                {
                    "name": "tumor",
                    "value": 23
                }
            ]
        },
        {
            "name": "C4",
            "children": [
                {
                    "name": "growth",
                    "value": 23
                },
                {
                    "name": "growth",
                    "value": 23
                }
            ]
        },
        {
            "name": "C5",
            "children": [
                {
                    "name": "cRGD-HL",
                    "value": 17
                },
                {
                    "name": "cRGD-HL",
                    "value": 17
                },
                {
                    "name": "cRGD-HL",
                    "value": 17
                },
                {
                    "name": "cRGD-HL",
                    "value": 17
                },
                {
                    "name": "cRGD-HL",
                    "value": 17
                },
                {
                    "name": "cRGD-HL",
                    "value": 17
                },
                {
                    "name": "cRGD-HL",
                    "value": 18
                },
                {
                    "name": "cRGD-HL",
                    "value": 17
                }
            ]
        },
        {
            "name": "C6",
            "children": [
                {
                    "name": "cRGDyK",
                    "value": 17
                },
                {
                    "name": "cRGDyK",
                    "value": 17
                }
            ]
        },
        {
            "name": "C7",
            "children": [
                {
                    "name": "angiogenic",
                    "value": 23
                },
                {
                    "name": "angiogenic",
                    "value": 23
                },
                {
                    "name": "angiogenic",
                    "value": 23
                }
            ]
        },
        {
            "name": "C8",
            "children": [
                {
                    "name": "activity",
                    "value": 23
                },
                {
                    "name": "activity",
                    "value": 23
                }
            ]
        },
        {
            "name": "C9",
            "children": [
                {
                    "name": "endothelial cell",
                    "value": 23
                },
                {
                    "name": "endothelial cells",
                    "value": 23
                },
                {
                    "name": "endothelial cells",
                    "value": 23
                }
            ]
        },
        {
            "name": "C10",
            "children": [
                {
                    "name": "vitronectin",
                    "value": 20
                },
                {
                    "name": "vitronectin",
                    "value": 19
                }
            ]
        },
        {
            "name": "C11",
            "children": [
                {
                    "name": "alpha(v)beta(3) integrin",
                    "value": 15
                },
                {
                    "name": "alpha(v)beta(3) integrin",
                    "value": 15
                },
                {
                    "name": "alpha(v)beta(3)",
                    "value": 16
                }
            ]
        },
        {
            "name": "C12",
            "children": [
                {
                    "name": "enhanced",
                    "value": 23
                },
                {
                    "name": "enhanced",
                    "value": 23
                }
            ]
        },
        {
            "name": "C13",
            "children": [
                {
                    "name": "effect",
                    "value": 23
                },
                {
                    "name": "effect",
                    "value": 23
                }
            ]
        }
    ]
}